Metadata-Version: 2.1
Name: localstack-extension-hello-world
Version: 0.1.1
Summary: LocalStack Extension: Hello World
Home-page: https://github.com/localstack/localstack-extensions/tree/main/hello-world
Author: Thomas Rausch
Author-email: thomas@localstack.cloud
Provides-Extra: dev
Requires-Dist: localstack-core >=1.0 ; extra == 'dev'
